[
  {
    "texto1": "además",
    "texto2": "también",
    "texto3": "besides",
    "texto4": "I have no other family besides my parents"
  },
  {
    "texto1": "bastante",
    "texto2": "mas bien",
    "texto3": "rather",
    "texto4": "she'd rather die than cause a scene"
  },
  {
    "texto1": "Voltear",
    "texto2": "cambiar",
    "texto3": "Flips",
    "texto4": "The acrobat performed an incredible series of flips and twists"
  },
  {
    "texto1": "programar",
    "texto2": "cronograma",
    "texto3": "schedule",
    "texto4": "we have drawn up an engineering schedule"
  },
  {
    "texto1": "Mezclar",
    "texto2": "Reorganizar",
    "texto3": "shuffle",
    "texto4": "I like to shuffle my playlist to discover new songs"
  },
  {
    "texto1": "tirar",
    "texto2": "lanzar",
    "texto3": "throw",
    "texto4": "She thrown the ball to her friend"
  },
  {
    "texto1": "ataque/golpe",
    "texto2": "trazar",
    "texto3": "stroke",
    "texto4": "the paint had been applied in careful strokes"
  },
  {
    "texto1": "Aparte",
    "texto2": "comentario",
    "texto3": "aside",
    "texto4": "She set some money aside for a rainy day"
  },
  {
    "texto1": "desvanecer",
    "texto2": "desaparecer",
    "texto3": "Fading",
    "texto4": "The colors of the sunset were fading"
  },
  {
    "texto1": "Obtener/Entender",
    "texto2": "Llegar/recibir",
    "texto3": "Gets",
    "texto4": "The bus usually gets to the station at 9 AM"
  },
  {
    "texto1": "configurado",
    "texto2": "enlatado",
    "texto3": "canned",
    "texto4": "transition pre canned"
  },
  {
    "texto1": "directo",
    "texto2": "sencillo",
    "texto3": "straightforward",
    "texto4": "The problem had a straightforward solution"
  },
  {
    "texto1": "acuerdo/comerciar",
    "texto2": "trato/reparto",
    "texto3": "deal",
    "texto4": "Working mothers get a raw deal"
  },
  {
    "texto1": "parecer",
    "texto2": "impresion",
    "texto3": "seem",
    "texto4": "She seems happy today"
  },
  {
    "texto1": "cambio dir",
    "texto2": "rotar",
    "texto3": "turn",
    "texto4": "The Earth turns on its axis"
  },
  {
    "texto1": "oportunidad",
    "texto2": "encender",
    "texto3": "turn",
    "texto4": "It's your turn to speak"
  },
  {
    "texto1": "conducir",
    "texto2": "dirigir",
    "texto3": "lead",
    "texto4": "She will lead the team in the project"
  },
  {
    "texto1": "causas",
    "texto2": "pista",
    "texto3": "lead",
    "texto4": "His actions may lead to consequences."
  },
  {
    "texto1": "rostro",
    "texto2": "afrontar",
    "texto3": "face",
    "texto4": "She had to face the challenges head-on"
  },
  {
    "texto1": "part delante",
    "texto2": "girar",
    "texto3": "house faces the ocean",
    "texto4": "The mountain faces the valley."
  },
  {
    "texto1": "esfuerzo",
    "texto2": "pelea",
    "texto3": "struggle",
    "texto4": "Her life has been a constant struggle"
  },
  {
    "texto1": "competir",
    "texto2": "dificultad",
    "texto3": "struggle",
    "texto4": "Students often struggle with math"
  },
  {
    "texto1": "derrotar",
    "texto2": "superar",
    "texto3": "overcome",
    "texto4": "The new technology will overcome the limitations"
  },
  {
    "texto1": "característica",
    "texto2": "Aparecer",
    "texto3": "feature",
    "texto4": "The singer will feature in tonight's concert"
  },
  {
    "texto1": "Entregar",
    "texto2": "Rendirse",
    "texto3": "submit",
    "texto4": "They were forced to submit to the enemy's control"
  },
  {
    "texto1": "molestar",
    "texto2": "tomar tiempo",
    "texto3": "bother",
    "texto4": "She'll bother to cook a special meal"
  },
  {
    "texto1": "citar",
    "texto2": "estimacion",
    "texto3": "quote",
    "texto4": "The contractor will quote a price"
  },
  {
    "texto1": "vinculo",
    "texto2": "enlace",
    "texto3": "link",
    "texto4": "Click on the link to visit the website"
  },
  {
    "texto1": "relacion",
    "texto2": "conectar",
    "texto3": "link",
    "texto4": "You can link these two documents"
  },
  {
    "texto1": "asunto",
    "texto2": "problema",
    "texto3": "issue",
    "texto4": "The main issue of the meeting"
  },
  {
    "texto1": "publicacion",
    "texto2": "asunto legal",
    "texto3": "issue",
    "texto4": "The court will address the issue"
  },
  {
    "texto1": "permitirse",
    "texto2": "costearse",
    "texto3": "afford",
    "texto4": "We can't afford to ignore climate change any longer"
  }
]
